tpds_utils_env_var/__init__.py
tpds_utils_env_var/env_var.py
tpds_utils_env_var-0.0.5.dist-info/LICENSE
tpds_utils_env_var-0.0.5.dist-info/METADATA
tpds_utils_env_var-0.0.5.dist-info/WHEEL
tpds_utils_env_var-0.0.5.dist-info/top_level.txt
tpds_utils_env_var-0.0.5.dist-info/RECORD
