Metadata-Version: 2.1
Name: tpds-utils-env-var
Version: 0.0.5
Summary: TPDS environment variable management.
Author-email: TPDS <dataservices@travelpassgroup.com>
Classifier: Programming Language :: Python :: 3
Classifier: License :: OSI Approved :: MIT License
Classifier: Operating System :: OS Independent
Requires-Python: >=3.8
License-File: LICENSE
